{"version":1,"resource":"file:///home/louis/gits/ysyx/ysyx-workbench/dlco-test/exp03/vsrc/alu4.v","entries":[{"id":"CkXG.v","timestamp":1713954646632},{"id":"xtB8.v","timestamp":1713954658529},{"id":"1nDx.v","timestamp":1713954668545},{"id":"YIKr.v","timestamp":1713956009139},{"id":"SZpS.v","timestamp":1713956056941},{"id":"aJeU.v","timestamp":1713956070274},{"id":"OkpT.v","timestamp":1713956109632},{"id":"IHcN.v","timestamp":1713956131881},{"id":"NcI2.v","timestamp":1713956180644},{"id":"9eMK.v","timestamp":1713956342067},{"id":"LS1E.v","timestamp":1713956442483},{"id":"1Yas.v","timestamp":1713956485488},{"id":"qHfY.v","timestamp":1713956503809},{"id":"5UK1.v","timestamp":1713956542323},{"id":"WRGw.v","timestamp":1713956560455},{"id":"dEmN.v","timestamp":1713956750990},{"id":"63Il.v","timestamp":1713956907878},{"id":"U43e.v","timestamp":1713956948756},{"id":"wYUW.v","timestamp":1713957021758},{"id":"KqhZ.v","timestamp":1713957039234},{"id":"yxSH.v","timestamp":1713957052298},{"id":"o1hV.v","timestamp":1713957064999},{"id":"Uu4l.v","source":"renamed.source","timestamp":1713957095276},{"id":"MniG.v","timestamp":1713957097728},{"id":"lSQE.v","timestamp":1713957275753},{"id":"BOMs.v","timestamp":1713957308597},{"id":"MDjx.v","timestamp":1713957454473},{"id":"m7FZ.v","timestamp":1713957469214},{"id":"sQB0.v","timestamp":1713957970282},{"id":"rW4t.v","timestamp":1713960206686},{"id":"wtT9.v","timestamp":1713960416391},{"id":"rLau.v","timestamp":1713961545281},{"id":"BKPx.v","timestamp":1713961716685},{"id":"tuD3.v","timestamp":1713961741021},{"id":"uuFG.v","timestamp":1713961986840},{"id":"sZ2d.v","timestamp":1713962122019},{"id":"cwur.v","timestamp":1713962279780},{"id":"cntD.v","timestamp":1713963833621},{"id":"0FWX.v","timestamp":1713963849309},{"id":"saUd.v","timestamp":1713964654713},{"id":"iHhS.v","source":"undoRedo.source","timestamp":1713964669358},{"id":"cN1C.v","timestamp":1713964689134},{"id":"Bmzk.v","timestamp":1713964699550},{"id":"UNPl.v","source":"renamed.source","timestamp":1713964738871},{"id":"zehN.v","timestamp":1713964741624},{"id":"gynR.v","timestamp":1713965848928},{"id":"CiVp.v","timestamp":1713965870808},{"id":"1pcN.v","timestamp":1713965898224},{"id":"gv2c.v","timestamp":1713965915432},{"id":"ggpy.v","timestamp":1713965960957}]}